X100GeGccXiaoJiqiao/README.md
X100GeGccXiaoJiqiao/__init__.py
X100GeGccXiaoJiqiao/__main__.py
X100GeGccXiaoJiqiao/file.epub
X100GeGccXiaoJiqiao/index.html
X100GeGccXiaoJiqiao/css/__init__.py
X100GeGccXiaoJiqiao/css/annotations.css
X100GeGccXiaoJiqiao/css/main.css
X100GeGccXiaoJiqiao/css/normalize.css
X100GeGccXiaoJiqiao/css/popup.css
X100GeGccXiaoJiqiao/font/__init__.py
X100GeGccXiaoJiqiao/font/fontello.eot
X100GeGccXiaoJiqiao/font/fontello.svg
X100GeGccXiaoJiqiao/font/fontello.ttf
X100GeGccXiaoJiqiao/font/fontello.woff
X100GeGccXiaoJiqiao/img/__init__.py
X100GeGccXiaoJiqiao/img/annotator-glyph-sprite.png
X100GeGccXiaoJiqiao/img/annotator-icon-sprite.png
X100GeGccXiaoJiqiao/img/apple-touch-icon.png
X100GeGccXiaoJiqiao/img/cancelfullscreen.png
X100GeGccXiaoJiqiao/img/close.png
X100GeGccXiaoJiqiao/img/fullscreen.png
X100GeGccXiaoJiqiao/img/loader.gif
X100GeGccXiaoJiqiao/img/menu-icon.png
X100GeGccXiaoJiqiao/img/save.png
X100GeGccXiaoJiqiao/img/saved.png
X100GeGccXiaoJiqiao/img/settings-s.png
X100GeGccXiaoJiqiao/img/settings.png
X100GeGccXiaoJiqiao/img/star.png
X100GeGccXiaoJiqiao/js/__init__.py
X100GeGccXiaoJiqiao/js/epub.js
X100GeGccXiaoJiqiao/js/epub.min.js
X100GeGccXiaoJiqiao/js/epub.min.map
X100GeGccXiaoJiqiao/js/hooks.min.js
X100GeGccXiaoJiqiao/js/hooks.min.map
X100GeGccXiaoJiqiao/js/reader.js
X100GeGccXiaoJiqiao/js/reader.js.map
X100GeGccXiaoJiqiao/js/reader.min.js
X100GeGccXiaoJiqiao/js/reader.min.map
X100GeGccXiaoJiqiao/js/hooks/__init__.py
X100GeGccXiaoJiqiao/js/hooks/extensions/__init__.py
X100GeGccXiaoJiqiao/js/hooks/extensions/highlight.js
X100GeGccXiaoJiqiao/js/libs/__init__.py
X100GeGccXiaoJiqiao/js/libs/jquery.min.js
X100GeGccXiaoJiqiao/js/libs/localforage.min.js
X100GeGccXiaoJiqiao/js/libs/screenfull.js
X100GeGccXiaoJiqiao/js/libs/screenfull.min.js
X100GeGccXiaoJiqiao/js/libs/zip.min.js
X100GeGccXiaoJiqiao/js/plugins/__init__.py
X100GeGccXiaoJiqiao/js/plugins/hypothesis.js
X100GeGccXiaoJiqiao/js/plugins/search.js
x100_ge_gcc_xiao_jiqiao-2024.2.29.0.dist-info/METADATA
x100_ge_gcc_xiao_jiqiao-2024.2.29.0.dist-info/WHEEL
x100_ge_gcc_xiao_jiqiao-2024.2.29.0.dist-info/entry_points.txt
x100_ge_gcc_xiao_jiqiao-2024.2.29.0.dist-info/top_level.txt
x100_ge_gcc_xiao_jiqiao-2024.2.29.0.dist-info/RECORD
